adafruit_scd4x.py
adafruit_circuitpython_scd4x-1.4.9.dist-info/licenses/LICENSE
adafruit_circuitpython_scd4x-1.4.9.dist-info/METADATA
adafruit_circuitpython_scd4x-1.4.9.dist-info/WHEEL
adafruit_circuitpython_scd4x-1.4.9.dist-info/top_level.txt
adafruit_circuitpython_scd4x-1.4.9.dist-info/RECORD
