Metadata-Version: 2.4
Name: adafruit-circuitpython-scd4x
Version: 1.4.9
Summary: Driver for Sensirion SCD4X CO2 sensor
Author-email: Adafruit Industries <circuitpython@adafruit.com>
License: MIT
Project-URL: Homepage, https://github.com/adafruit/Adafruit_CircuitPython_SCD4X.git
Keywords: adafruit,blinka,circuitpython,micropython,scd4x,CO2,humidity,temperature,sensor,SCD40,SCD41
Classifier: Intended Audience :: Developers
Classifier: Topic :: Software Development :: Libraries
Classifier: Topic :: Software Development :: Embedded Systems
Classifier: Topic :: System :: Hardware
Classifier: License :: OSI Approved :: MIT License
Classifier: Programming Language :: Python :: 3
License-File: LICENSE
Requires-Dist: Adafruit-Blinka
Requires-Dist: adafruit-circuitpython-busdevice
Provides-Extra: optional
Dynamic: license-file
